setup.py
nebri_auth/__init__.py
nebri_auth/nebri_auth.py
python_nebri_authentication.egg-info/PKG-INFO
python_nebri_authentication.egg-info/SOURCES.txt
python_nebri_authentication.egg-info/dependency_links.txt
python_nebri_authentication.egg-info/requires.txt
python_nebri_authentication.egg-info/top_level.txt