Metadata-Version: 1.0
Name: python-nebri-authentication
Version: 0.1.1
Summary: python-nebri-authentication is a simple and easy-to-use package to make authenticated nebri api requests from a python application.
Home-page: http://github.com/briem-bixly/python-nebri-authentication/
Author: briem-bixly
Author-email: UNKNOWN
License: UNKNOWN
Platform: UNKNOWN
